{
  "sp500": [
    {
      "url": "https://fortune.com/2025/11/29/stock-market-outlook-santa-claus-rally-sp500-forecast-8000-2026/",
      "title": "Santa is coming to Wall Street early this season, and analysts say 2026 is shaping up to be another big year of gains",
      "source": "Fortune",
      "date": "11/29/2025, 10:00 PM, +0000 UTC",
      "snippet": ""
    },
    {
      "url": "https://finance.yahoo.com/news/historical-market-pattern-just-ended-183500325.html",
      "title": "This Historical Market Pattern Just Ended, and It Could Be a Precursor to a Market Crash",
      "source": "Yahoo Finance",
      "date": "11/29/2025, 06:35 PM, +0000 UTC",
      "snippet": ""
    },
    {
      "url": "https://www.investopedia.com/sandisk-joins-the-s-and-p-500-today-its-stock-has-been-a-huge-gainer-this-year-sndk-11858604",
      "title": "Sandisk Joins the S&P 500 Today. Its Stock Has Been a Huge Gainer This Year.",
      "source": "Investopedia",
      "date": "11/28/2025, 03:42 PM, +0000 UTC",
      "snippet": ""
    },
    {
      "url": "https://seekingalpha.com/article/4848621-the-7-biggest-s-and-p-500-stocks-might-be-all-we-need",
      "title": "The 7 Biggest S&P 500 Stocks Might Be All We Need. (NYSEARCA:IVV)",
      "source": "Seeking Alpha",
      "date": "11/29/2025, 02:00 PM, +0000 UTC",
      "snippet": ""
    },
    {
      "url": "https://www.reuters.com/business/finance/jp-morgan-sees-sp-500-7500-by-end-2026-double-digit-gain-here-2025-11-26/",
      "title": "J.P. Morgan sees S&P 500 at 7,500 by end 2026, double-digit gain from here",
      "source": "Reuters",
      "date": "11/26/2025, 03:44 PM, +0000 UTC",
      "snippet": ""
    }
  ],
  "treasury": [
    {
      "url": "https://www.reuters.com/world/us/bessent-says-us-treasury-working-cut-off-federal-benefits-illegal-aliens-2025-11-28/",
      "title": "Bessent says US Treasury working to cut off federal benefits to 'illegal aliens'",
      "source": "Reuters",
      "date": "11/28/2025, 07:06 PM, +0000 UTC",
      "snippet": ""
    },
    {
      "url": "https://www.cnbc.com/2025/11/28/us-treasury-yields-trading-disrupted-after-cme-halt.html",
      "title": "Treasury yields inch higher after CME trading disruption",
      "source": "CNBC",
      "date": "11/28/2025, 12:01 PM, +0000 UTC",
      "snippet": ""
    },
    {
      "url": "https://www.ft.com/content/e23fccca-605f-4c38-b03c-7724e7221117",
      "title": "Voice trading makes a comeback in $30tn Treasury market",
      "source": "Financial Times",
      "date": "11/26/2025, 04:00 AM, +0000 UTC",
      "snippet": ""
    },
    {
      "url": "https://www.bloomberg.com/news/features/2025-11-02/us-treasury-rally-stuns-wall-street-with-best-return-since-2020",
      "title": "Treasuries Rally Is Proving Trump’s ‘Sell America’ Critics Wrong",
      "source": "Bloomberg.com",
      "date": "11/02/2025, 07:00 AM, +0000 UTC",
      "snippet": ""
    },
    {
      "url": "https://www.cnbc.com/2025/11/12/us-treasury-yields-end-of-government-shutdown-nears-.html",
      "title": "Treasury yields move lower as end of the government shutdown nears",
      "source": "CNBC",
      "date": "11/12/2025, 08:00 AM, +0000 UTC",
      "snippet": ""
    }
  ],
  "oil": [
    {
      "url": "https://www.reuters.com/business/energy/swelling-supply-keep-oil-prices-under-strain-2026-2025-11-28/",
      "title": "Swelling supply to keep oil prices under strain in 2026",
      "source": "Reuters",
      "date": "11/28/2025, 11:38 AM, +0000 UTC",
      "snippet": ""
    },
    {
      "url": "https://finance.yahoo.com/news/oil-prices-expected-to-fall-in-2026-as-wall-street-sees-punishing-oversupply-risking-return-to-covid-levels-134609564.html",
      "title": "Oil prices expected to fall in 2026 as Wall Street sees 'punishing oversupply' risking return to COVID levels",
      "source": "Yahoo Finance",
      "date": "11/28/2025, 01:46 PM, +0000 UTC",
      "snippet": ""
    },
    {
      "url": "https://www.reuters.com/business/energy/oil-prices-drop-expectations-ceasefire-ukraine-unlocking-russian-supply-2025-11-27/",
      "title": "Oil prices settle up in low volume on US holiday; Russia-Ukraine talks in focus",
      "source": "Reuters",
      "date": "11/27/2025, 07:02 PM, +0000 UTC",
      "snippet": ""
    },
    {
      "url": "https://www.reuters.com/business/energy/saudi-arabia-may-reduce-january-oil-prices-asia-five-year-low-2025-11-28/",
      "title": "Saudi Arabia may reduce January oil prices to Asia to five-year low",
      "source": "Reuters",
      "date": "11/28/2025, 07:33 AM, +0000 UTC",
      "snippet": ""
    },
    {
      "url": "https://finance.yahoo.com/news/petrobras-cuts-capex-plan-lower-103000170.html",
      "title": "Petrobras Cuts Capex Plan on Lower Oil Prices",
      "source": "Yahoo Finance",
      "date": "11/28/2025, 10:30 AM, +0000 UTC",
      "snippet": ""
    }
  ],
  "gold": [
    {
      "url": "https://finance.yahoo.com/personal-finance/investing/article/gold-price-today-friday-november-28-gold-rises-with-volatility-amid-outage-123653352.html",
      "title": "Gold price today, Friday, November 28: Gold rises with volatility amid outage",
      "source": "Yahoo Finance",
      "date": "11/28/2025, 03:24 PM, +0000 UTC",
      "snippet": ""
    },
    {
      "url": "https://finance.yahoo.com/personal-finance/investing/article/gold-price-today-wednesday-november-26-gold-surpasses-4170-on-expectations-for-lower-interest-rates-123653251.html",
      "title": "Gold price today, Wednesday, November 26: Gold surpasses $4,170 on expectations for lower interest rates",
      "source": "Yahoo Finance",
      "date": "11/26/2025, 12:57 PM, +0000 UTC",
      "snippet": ""
    },
    {
      "url": "https://fortune.com/article/current-price-of-gold-11-26-2025/",
      "title": "Current price of gold as of November 26, 2025",
      "source": "Fortune",
      "date": "11/26/2025, 03:34 PM, +0000 UTC",
      "snippet": ""
    },
    {
      "url": "https://www.cnbc.com/2025/11/28/goldman-sachs-investor-poll-gold-can-top-5k-in-2026-.html",
      "title": "Goldman Sachs polled institutional investors on gold, and found many expect it to hit $5K next year",
      "source": "CNBC",
      "date": "11/28/2025, 03:46 PM, +0000 UTC",
      "snippet": ""
    },
    {
      "url": "https://finance.yahoo.com/news/gold-clinches-fourth-straight-monthly-gain-closes-in-on-record-high-as-markets-solidify-rate-cut-bets-181701120.html",
      "title": "Gold clinches fourth straight monthly gain, closes in on record high as markets solidify rate cut bets",
      "source": "Yahoo Finance",
      "date": "11/28/2025, 06:17 PM, +0000 UTC",
      "snippet": ""
    }
  ],
  "dollar": [
    {
      "url": "https://www.bloomberg.com/news/articles/2025-11-28/india-rupee-falls-to-record-on-importer-dollar-buys-trade-worry",
      "title": "INR USD: India Rupee Falls to Record on Importer Dollar Buys, Trade Worry",
      "source": "Bloomberg.com",
      "date": "11/28/2025, 10:42 AM, +0000 UTC",
      "snippet": ""
    },
    {
      "url": "https://seekingalpha.com/article/4848197-bitcoin-this-time-is-already-different",
      "title": "Bitcoin: This Time Is Already Different (Technical Analysis)",
      "source": "Seeking Alpha",
      "date": "11/27/2025, 10:26 AM, +0000 UTC",
      "snippet": ""
    },
    {
      "url": "https://finance.yahoo.com/news/copper-products-market-size-reach-102800535.html",
      "title": "Copper Products Market Size to Reach USD 651.19 Bn by 2035",
      "source": "Yahoo Finance",
      "date": "11/28/2025, 10:28 AM, +0000 UTC",
      "snippet": ""
    },
    {
      "url": "https://seekingalpha.com/article/4848699-how-us-dollar-weakness-could-buoy-emerging-markets",
      "title": "How U.S. Dollar Weakness Could Buoy Emerging Markets",
      "source": "Seeking Alpha",
      "date": "11/29/2025, 08:20 AM, +0000 UTC",
      "snippet": ""
    },
    {
      "url": "https://www.bloomberg.com/news/articles/2025-11-27/inr-usd-why-is-india-rupee-so-weak-what-does-it-mean-for-prices-incomes",
      "title": "How India’s Rupee Ended Up as Asia’s Worst Currency This Year",
      "source": "Bloomberg.com",
      "date": "11/27/2025, 05:53 AM, +0000 UTC",
      "snippet": ""
    }
  ],
  "lastUpdated": "2025-11-29T23:13:16.885Z"
}