{
  "sp500": [
    {
      "url": "https://finance.yahoo.com/news/live/stock-market-today-dow-sp-500-notch-records-nasdaq-gains-as-wall-street-flies-high-into-christmas-holiday-180542226.html",
      "title": "Stock market today: Dow, S&P 500 notch records, Nasdaq gains as Wall Street flies high into Christmas holiday",
      "source": "Yahoo Finance",
      "date": "12/24/2025, 07:42 PM, +0000 UTC",
      "snippet": ""
    },
    {
      "url": "https://www.investopedia.com/dow-jones-today-12242025-11875790",
      "title": "Dow Jones Today: S&P 500 Sets All-Time High, Stocks Rise in Shortened Session; Gold, Silver Hit New Records",
      "source": "Investopedia",
      "date": "12/24/2025, 07:20 PM, +0000 UTC",
      "snippet": ""
    },
    {
      "url": "https://seekingalpha.com/article/4855667-how-the-s-and-p-500-reaches-10000-in-2026",
      "title": "How The S&P 500 Reaches 10,000 In 2026 (NYSEARCA:SPY)",
      "source": "Seeking Alpha",
      "date": "12/24/2025, 07:07 PM, +0000 UTC",
      "snippet": ""
    },
    {
      "url": "https://www.wsj.com/finance/stocks/global-stocks-markets-dow-update-d6f4947f?gaa_at=eafs&gaa_n=AWEtsqfEnsVfhX425S-lmni3LrSm5z6Hsoh-xfmjrQZDL_ZAaS6nklqb8QO7&gaa_ts=694c774b&gaa_sig=7Tfk4qwxe3_6VS4QsPBV0SW2sEknnl44QRjOlVD1iYjbM3qcpd1AtPcMmF2hnjoAG9XOnZqkrO2LrilAMaBDDA%3D%3D",
      "title": "Nike Climb Boosts Dow, S&P 500",
      "source": "The Wall Street Journal",
      "date": "12/24/2025, 07:03 PM, +0000 UTC",
      "snippet": ""
    },
    {
      "url": "https://www.reuters.com/world/china/global-markets-wrapup-1-pix-2025-12-24/",
      "title": "S&P 500, Dow hit all-time closing highs; gold, silver touch records",
      "source": "Reuters",
      "date": "12/24/2025, 06:33 PM, +0000 UTC",
      "snippet": ""
    }
  ],
  "treasury": [
    {
      "url": "https://www.reuters.com/markets/us/surprise-asset-year-30-year-us-treasury-bond-2025-12-22/",
      "title": "Surprise asset of the year? The 30-year US Treasury bond",
      "source": "Reuters",
      "date": "12/23/2025, 12:30 AM, +0000 UTC",
      "snippet": ""
    },
    {
      "url": "https://www.cnbc.com/2025/12/23/us-treasury-yields-decline-ahead-of-key-debt-auctions.html",
      "title": "10-year Treasury yield is little changed after latest U.S. GDP report",
      "source": "CNBC",
      "date": "12/23/2025, 08:21 AM, +0000 UTC",
      "snippet": ""
    },
    {
      "url": "https://www.bloomberg.com/news/articles/2025-12-23/treasuries-slip-as-us-gdp-posts-fastest-growth-in-two-years",
      "title": "Treasuries Slip as US GDP Posts Fastest Growth in Two Years",
      "source": "Bloomberg",
      "date": "12/23/2025, 08:44 PM, +0000 UTC",
      "snippet": ""
    },
    {
      "url": "https://www.cnbc.com/2025/12/22/treasury-yields-edge-higher-as-holiday-shortened-week-starts.html",
      "title": "U.S. Treasury yields edge higher as investors prepare for holiday-shortened week",
      "source": "CNBC",
      "date": "12/22/2025, 09:24 AM, +0000 UTC",
      "snippet": ""
    },
    {
      "url": "https://www.cnbc.com/2025/12/24/10-year-treasury-yields-dip-as-stronger-gdp-data-clouds-rate-path.html",
      "title": "10-year Treasury yield moves lower as investors mull rates path following strong GDP data",
      "source": "CNBC",
      "date": "12/24/2025, 09:24 AM, +0000 UTC",
      "snippet": ""
    }
  ],
  "oil": [
    {
      "url": "https://www.reuters.com/markets/commodities/china-overtakes-opec-main-oil-price-maker-2025-12-22/",
      "title": "China overtakes OPEC+ as the main oil price maker",
      "source": "Reuters",
      "date": "12/23/2025, 01:00 PM, +0000 UTC",
      "snippet": ""
    },
    {
      "url": "https://www.barrons.com/articles/oil-prices-stocks-valuations-77320288?gaa_at=eafs&gaa_n=AWEtsqcrl8lvaW8SNP3V6q7jIg9fBRqdwZxzZugJppE2owLJWsUfFu0CYl-U&gaa_ts=694c7754&gaa_sig=gqioDUWL-Xg1FtJR8fqiUfyNGZccGhqrnmnST1m5AkO9w-5aFN8rRQn7cY7eIeq5EzDOlybzIf0FHNztFFKINA%3D%3D",
      "title": "Oil Prices Crashed This Year. Why the Stocks Have Held Up.",
      "source": "Barron's",
      "date": "12/24/2025, 06:09 PM, +0000 UTC",
      "snippet": ""
    },
    {
      "url": "https://www.reuters.com/business/energy/oil-prices-gain-us-interception-venezuelan-oil-tanker-over-weekend-2025-12-22/",
      "title": "Oil settles higher on risk of disruptions to Venezuela, Russia supply",
      "source": "Reuters",
      "date": "12/22/2025, 08:34 PM, +0000 UTC",
      "snippet": ""
    },
    {
      "url": "https://www.reuters.com/world/middle-east/most-gulf-markets-gain-oil-price-rise-strong-us-growth-2025-12-24/",
      "title": "Most Gulf markets ease despite firmer oil prices",
      "source": "Reuters",
      "date": "12/24/2025, 01:29 PM, +0000 UTC",
      "snippet": ""
    },
    {
      "url": "https://www.reuters.com/business/energy/oil-slips-market-weighs-venezuela-russia-supply-risks-2025-12-23/",
      "title": "Oil up as market weighs strong US economic growth, supply risks",
      "source": "Reuters",
      "date": "12/23/2025, 10:45 PM, +0000 UTC",
      "snippet": ""
    }
  ],
  "gold": [
    {
      "url": "https://finance.yahoo.com/personal-finance/investing/article/why-is-silver-outperforming-gold-what-to-know-before-you-invest-231615030.html",
      "title": "Why is silver outperforming gold? What to know before you invest.",
      "source": "Yahoo Finance",
      "date": "12/24/2025, 03:48 PM, +0000 UTC",
      "snippet": ""
    },
    {
      "url": "https://www.reuters.com/world/africa/south-african-rand-climbs-further-gold-price-2025-12-23/",
      "title": "South African rand climbs further on gold price",
      "source": "Reuters",
      "date": "12/23/2025, 08:17 AM, +0000 UTC",
      "snippet": ""
    },
    {
      "url": "https://www.bloomberg.com/news/articles/2025-12-22/gold-price-record-why-us-rate-cut-bets-safe-haven-appeal-are-fueling-rally",
      "title": "How Gold’s Safe-Haven Appeal Is Fueling Record Prices",
      "source": "Bloomberg",
      "date": "12/22/2025, 03:16 PM, +0000 UTC",
      "snippet": ""
    },
    {
      "url": "https://www.investopedia.com/why-many-experts-believe-gold-prices-will-surpass-usd5000-in-2026-11858606",
      "title": "Why Some Experts Believe Gold Prices Could Reach $5,000 in 2026",
      "source": "Investopedia",
      "date": "11/28/2025, 08:00 AM, +0000 UTC",
      "snippet": ""
    },
    {
      "url": "https://www.bloomberg.com/news/articles/2025-12-23/gold-steadies-near-record-high-as-venezuela-tensions-persist",
      "title": "Gold Soars Above $4,500 for First Time on Geopolitics, Rates",
      "source": "Bloomberg",
      "date": "12/24/2025, 08:18 PM, +0000 UTC",
      "snippet": ""
    }
  ],
  "dollar": [
    {
      "url": "https://www.bloomberg.com/news/articles/2025-12-22/krw-usd-why-is-south-korea-worried-about-the-weak-won",
      "title": "KRW/USD: Why is South Korea Worried About the Weak Won?",
      "source": "Bloomberg",
      "date": "12/22/2025, 09:02 AM, +0000 UTC",
      "snippet": ""
    },
    {
      "url": "https://www.reuters.com/world/asia-pacific/dollar-set-worst-year-since-2003-rate-outlooks-diverge-2025-12-24/",
      "title": "Yen stronger as traders wary of intervention",
      "source": "Reuters",
      "date": "12/24/2025, 05:44 PM, +0000 UTC",
      "snippet": ""
    },
    {
      "url": "https://finance.yahoo.com/news/billionaire-michael-saylor-strategy-boosts-132133780.html",
      "title": "Billionaire Michael Saylor’s Strategy Boosts USD Reserves by $748M to $2.19B",
      "source": "Yahoo Finance",
      "date": "12/22/2025, 01:21 PM, +0000 UTC",
      "snippet": ""
    },
    {
      "url": "https://seekingalpha.com/news/4535038-santa-rally-leaves-bitcoin-behind",
      "title": "Santa rally leaves bitcoin behind (BTC-USD:Cryptocurrency)",
      "source": "Seeking Alpha",
      "date": "12/24/2025, 03:25 PM, +0000 UTC",
      "snippet": ""
    },
    {
      "url": "https://www.reuters.com/world/asia-pacific/us-dollar-trims-losses-after-stronger-than-expected-growth-data-2025-12-23/",
      "title": "US dollar retreats as prospect of Fed rate cuts overshadows growth data",
      "source": "Reuters",
      "date": "12/23/2025, 08:04 PM, +0000 UTC",
      "snippet": ""
    }
  ],
  "lastUpdated": "2025-12-24T23:14:09.980Z"
}